{"name":"Walter Michelin","tagline":"Computer Science Student at The College of New Jersey","body":"Walter Michelin\r\n(732)-597-0253 \r\n\r\nMichelw2@tcnj.edu\r\n\r\n440 Ship Ave, Beachwood, New Jersey\r\n\r\nwaltermichelin.com\r\n\t\r\nEDUCATION\t\r\n\r\nThe College of New Jersey, Ewing, New Jersey\t\r\n\t\r\nMajor: Computer Science, Class of 2015\r\n\r\nRelevant Course Work: Software Engineering, Data Structures\r\n\r\nOcean County College, Toms River, New Jersey\r\n\r\nAssociates in Business Administration, May 2013\r\n\r\nDistinctions: Graduated Cum Laude, Dean’s List\r\n\t\r\nEXPERIENCE \t\r\n\r\nSaker ShopRites Incorporated\t\t\t\t\t\t\t\r\n\t\t\tBookkeeper    \t\t    \t\t   Toms River, NJ                    \t          Aug’11- Jan’14\r\n\r\n•\tManaged storewide cash inflow. \r\n\r\n•\tCoordinated reconciliation of store register accounts.\r\n\r\n•\tPromoted from cashier within one month of employment.\r\n\r\nThe College of New Jersey\t\t\t\t     \t      \r\n\t\t\tAccess Services Representative\t  Ewing, NJ\t             \t          Aug’13-Present\r\n\r\n•\tResponsible for handling student accounts.\r\n\r\n•\tCoordinate and handle circulation of various library materials.\r\n\r\nPROJECTS\t\t\r\n\r\nStudents Organizing Against Pollution \t                   \r\n\t\t\t\r\nDevelop a webapp for Habitat for Humanity\r\nJan’14-Present\r\n\r\n•\tCollaborate and work directly in small team oriented groups to better learn and understand the issues at hand working with Habitat for Humanity. \r\n\r\n•\tDevelop and implement various features of the SOAP web application. \r\n\r\n•\tWork under the supervision of Dr. Pulimood to learn and implement software engineering concepts and fundamentals. \r\n\t\t\t\r\n\r\nReddit Trends\r\n\r\nImplement an application to understand trending reddit topics\t           \r\nJan’14-Present\r\n\r\n•\tIn Python, create an application to communicate with both the Reddit and Twitter APIs to gather massive amounts of data from reddit.com, organize and analyze said data and present it in a digestible format on twitter.com.\r\n\r\n•\tLearn and better understand the Python language and take advantage of its excellent API support and design capabilities. \r\n\r\nACTIVITIES \t\r\n\r\nAssociation For Computing Machinery \t        \t\t\t         \r\nAug’13-Present\r\n\r\n•\tPlanning and coordination of Hack TCNJ.\r\n\r\n•\tCompeted in various hackathons against thousands of peers.\r\n\r\n•\tCollaborate with other members to learn new and relevant coding skills.\r\n\r\n\r\nTCNJ Men’s Club Lacrosse\t\t\t\t\t\t          Aug’13-Present\r\n\r\n•\tStarting Defenseman.\r\n\r\n•\tOrganization and planning of team activities.\r\n\r\n•\tTeamwork, leadership, and recruitment.\r\n\r\nSKILLS\t           \t\r\n\r\nProgramming Languages: \r\nPython, Java, C++, Objective-C.\r\nSoftware: \r\nLinux, Mac OSX, Windows, Microsoft Office. \r\nInterests: \r\nCoding, Constructing custom PCs for friends and family, Lacrosse, Hiking, Golf, Skiing.  \r\n\t\t\t\t\t\r\n\t\t\t\t\r\n\t\r\n\r\n\t \t\t\t\t\t\t\t\t\t\r\n\t\t\t\t\t\t\t\r\n\t\r\n","google":"","note":"Don't delete this file! It's used internally to help with page regeneration."}